GEO_ADPTC/DPTree.py
GEO_ADPTC/__init__.py
GEO_ADPTC/auxiliary.py
GEO_ADPTC/clustering.py
GEO_ADPTC/verify.py
GEO_ADPTC/visual.py
GEO_ADPTC-0.0.5.dist-info/COPYING
GEO_ADPTC-0.0.5.dist-info/LICENSE
GEO_ADPTC-0.0.5.dist-info/METADATA
GEO_ADPTC-0.0.5.dist-info/WHEEL
GEO_ADPTC-0.0.5.dist-info/top_level.txt
GEO_ADPTC-0.0.5.dist-info/RECORD
