Metadata-Version: 2.1
Name: GEO-ADPTC
Version: 0.0.5
Summary: Adaptive Density Peak Tree Clustering
Home-page: https://gitee.com/suilandcoder/geo_-adptc
Author: 
Author-email: 
License: UNKNOWN
Project-URL: Bug Tracker, https://gitee.com/suilandcoder/geo_-adptc/issues
Platform: UNKNOWN
Classifier: Programming Language :: Python :: 3
Classifier: License :: OSI Approved :: GNU General Public License v3 (GPLv3)
Classifier: Operating System :: OS Independent
Requires-Python: >=3.6
License-File: LICENSE
License-File: COPYING
Requires-Dist: cartopy (>=0.18.0)
Requires-Dist: numpy (>=1.19.5)
Requires-Dist: xarray (>=0.16.2)
Requires-Dist: pyclustertend (>=1.4.9)
Requires-Dist: scikit-learn
Requires-Dist: seaborn (>=0.11.1)
Requires-Dist: matplotlib (>=3.3.4)
Requires-Dist: basemap (>=1.2.2)
Requires-Dist: netcdf4 (>=1.5.6)
Requires-Dist: memory-profiler (>=0.60.0)
